ESRT/__init__.py
ESRT/test.py
ESRT/train.py
ESRT/utils.py
ESRT/util/__init__.py
ESRT/util/non.py
ESRT/util/nonlocal.py
ESRT/util/position.py
ESRT/util/tools.py
ESRT/util/transformer.py
axcorsrmri-1.0.0.dist-info/METADATA
axcorsrmri-1.0.0.dist-info/WHEEL
axcorsrmri-1.0.0.dist-info/top_level.txt
axcorsrmri-1.0.0.dist-info/RECORD
