Metadata-Version: 2.1
Name: axcorsrmri
Version: 1.0.0
Summary: UNKNOWN
Home-page: https://github.com/TechnionComputationalMRILab/AxCorSRMRI
Author: Technion Computational MRI Lab
Author-email: tcml.bme@gmail.com
License: UNKNOWN
Platform: UNKNOWN
Requires-Dist: numpy ==1.23.5
Requires-Dist: SimpleITK ==2.3.1
Requires-Dist: tensorflow <2.11
Requires-Dist: pandas ==1.3.5
Requires-Dist: tensorboard
Requires-Dist: torch ==1.9.0
Requires-Dist: protobuf ==3.14.0
Requires-Dist: torchvision ==0.10.0
Requires-Dist: piq ==0.7.0
Requires-Dist: matplotlib ==3.4.2
Requires-Dist: tqdm ==4.66.4
Requires-Dist: h5py >=2.9.0
Requires-Dist: wrapt >=1.11.0
Requires-Dist: scipy ==1.10.1
Requires-Dist: ipykernel ==6.14.0
Requires-Dist: jupyter ==1.0.0
